generates/__init__.py
generates-0.1.0.dist-info/DESCRIPTION.rst
generates-0.1.0.dist-info/LICENSE.txt
generates-0.1.0.dist-info/METADATA
generates-0.1.0.dist-info/RECORD
generates-0.1.0.dist-info/WHEEL
generates-0.1.0.dist-info/metadata.json
generates-0.1.0.dist-info/top_level.txt
