Metadata-Version: 2.0
Name: generates
Version: 0.1.0
Summary: Micro library providing generates decorator
Home-page: UNKNOWN
Author: Tuomas Suutari
Author-email: tuomas.suutari@anders.fi
License: MIT
Keywords: generates,context manager,generator
Platform: UNKNOWN
Classifier: Development Status :: 4 - Beta
Classifier: Intended Audience :: Developers
Classifier: Topic :: Software Development :: Libraries :: Python Modules
Classifier: License :: OSI Approved :: MIT License
Classifier: Programming Language :: Python :: 2
Classifier: Programming Language :: Python :: 2.7
Classifier: Programming Language :: Python :: 3
Classifier: Programming Language :: Python :: 3.4
Classifier: Programming Language :: Python :: 3.5
Classifier: Programming Language :: Python :: 3.6
